neldermead/__init__.py
neldermead/alg.py
neldermead-0.0.12.dist-info/METADATA
neldermead-0.0.12.dist-info/RECORD
neldermead-0.0.12.dist-info/WHEEL
neldermead-0.0.12.dist-info/top_level.txt
