Metadata-Version: 2.1
Name: neldermead
Version: 0.0.12
Summary: Nelder-Mead for numerical optimization in Python
Home-page: https://github.com/nmasahiro/neldermead
Author: Masahiro Nomura
Author-email: masahironomura5325@gmail.com
Maintainer: Masahiro Nomura
Maintainer-email: masahironomura5325@gmail.com
License: MIT
Keywords: optimization,Nelder-Mead
Platform: UNKNOWN
Classifier: Intended Audience :: Science/Research
Classifier: Topic :: Scientific/Engineering
Classifier: Topic :: Scientific/Engineering :: Mathematics
Classifier: Topic :: Scientific/Engineering :: Artificial Intelligence
Classifier: Operating System :: OS Independent
Classifier: Programming Language :: Python :: 3
Classifier: License :: OSI Approved :: MIT License
Requires: numpy
